<?xml version="1.0" encoding="utf-8"?>
<root>
  <doclet-version-NOT-library-version>1.00</doclet-version-NOT-library-version>
  <b4x_version>11.80</b4x_version>
  <dependsOn>phone</dependsOn>
  <dependsOn>reflection</dependsOn>
  <class>
    <name>b4a.android.webkit.webkitsafebrowsingresponse</name>
    <shortname>WebkitSafeBrowsingResponse</shortname>
    <owner>process</owner>
    <method>
      <name>IsInitialized</name>
      <comment>Tests whether the object has been initialized.</comment>
      <returntype>boolean</returntype>
    </method>
    <method>
      <name DesignerName="BackToSafety">_backtosafety</name>
      <comment>Act as if the user clicked the "back to safety" button.
ParamBoolean As Boolean: true to enable Safe Browsing reporting.
Added in API level 27.
</comment>
      <returntype>String</returntype>
      <parameter>
        <name>ParamBoolean</name>
        <type>boolean</type>
      </parameter>
    </method>
    <method>
      <name DesignerName="Initialize">_initialize</name>
      <comment>Initializes the object.
Pass android.webkit.SafeBrowsingResponse from inline Java code to initialize an existing instance.
Added in API level 27.
</comment>
      <returntype>String</returntype>
      <parameter>
        <name>ba</name>
        <type>anywheresoftware.b4a.BA</type>
      </parameter>
      <parameter>
        <name>AndroidWebkitSafeBrowsingResponse</name>
        <type>Object</type>
      </parameter>
    </method>
    <method>
      <name DesignerName="Proceed">_proceed</name>
      <comment>Act as if the user clicked the "visit this unsafe site" button.
ParamBoolean As Boolean: true to enable Safe Browsing reporting.
Added in API level 27.
</comment>
      <returntype>String</returntype>
      <parameter>
        <name>ParamBoolean</name>
        <type>boolean</type>
      </parameter>
    </method>
    <method>
      <name DesignerName="ShowInterstitial">_showinterstitial</name>
      <comment>Display the default interstitial.
ParamBoolean As Boolean: true if the interstitial should show a reporting checkbox.
Added in API level 27.
</comment>
      <returntype>String</returntype>
      <parameter>
        <name>ParamBoolean</name>
        <type>boolean</type>
      </parameter>
    </method>
    <method>
      <name DesignerName="ToObject">_toobject</name>
      <comment>Returns Object as android.webkit.SafeBrowsingResponse which can be used in Java Code.
Added in API level 27.
</comment>
      <returntype>Object</returntype>
    </method>
    <field>
      <name DesignerName="ThreatType">_threattype</name>
      <returntype>int</returntype>
    </field>
    <field>
      <name DesignerName="ThreatTypeString">_threattypestring</name>
      <returntype>String</returntype>
    </field>
  </class>
  <version>1</version>
  <author>Ivica Golubovic</author>
</root>