<?xml version="1.0" encoding="utf-8"?>
<root>
  <doclet-version-NOT-library-version>1.00</doclet-version-NOT-library-version>
  <b4x_version>11.80</b4x_version>
  <dependsOn>reflection</dependsOn>
  <class>
    <name>b4a.android.webkit.webkitjspromptresult._webkitjsproperties</name>
    <shortname>WebkitJsProperties</shortname>
    <owner>process</owner>
    <method>
      <name>Initialize</name>
      <comment>Initializes the fields to their default value.</comment>
      <returntype>void</returntype>
    </method>
    <field>
      <name>IsInitialized</name>
      <comment>Tests whether the object has been initialized.</comment>
      <returntype>boolean</returntype>
    </field>
    <field>
      <name>Url</name>
      <returntype>String</returntype>
    </field>
    <field>
      <name>Message</name>
      <returntype>String</returntype>
    </field>
    <field>
      <name>DefaultValue</name>
      <returntype>String</returntype>
    </field>
  </class>
  <class>
    <name>b4a.android.webkit.webkitjspromptresult</name>
    <shortname>WebkitJsPromptResult</shortname>
    <owner>process</owner>
    <method>
      <name>IsInitialized</name>
      <comment>Tests whether the object has been initialized.</comment>
      <returntype>boolean</returntype>
    </method>
    <method>
      <name DesignerName="Confirm">_confirm</name>
      <comment>Added in API level 1.
</comment>
      <returntype>String</returntype>
      <parameter>
        <name>Result</name>
        <type>String</type>
      </parameter>
    </method>
    <method>
      <name DesignerName="Initialize">_initialize</name>
      <comment>Initializes the object.
Pass android.webkit.JsPromptResult from Java inline code to initialize instance.
Added in API level 1.
</comment>
      <returntype>String</returntype>
      <parameter>
        <name>ba</name>
        <type>anywheresoftware.b4a.BA</type>
      </parameter>
      <parameter>
        <name>AndroidWebkitJsPromptResult</name>
        <type>Object</type>
      </parameter>
    </method>
    <method>
      <name DesignerName="toObject">_toobject</name>
      <comment>Returns Object as android.webkit.JsPromptResult which can be used in inline Java Code.
Added in API level 1.
</comment>
      <returntype>Object</returntype>
    </method>
  </class>
  <class>
    <name>b4a.android.webkit.webkitjsresult</name>
    <shortname>WebkitJsResult</shortname>
    <owner>process</owner>
    <method>
      <name>IsInitialized</name>
      <comment>Tests whether the object has been initialized.</comment>
      <returntype>boolean</returntype>
    </method>
    <method>
      <name DesignerName="Cancel">_cancel</name>
      <comment>Handle the result if the user cancelled the dialog.
Added in API level 1.
</comment>
      <returntype>String</returntype>
    </method>
    <method>
      <name DesignerName="Confirm">_confirm</name>
      <comment>Handle a confirmation response from the user.
Added in API level 1.
</comment>
      <returntype>String</returntype>
    </method>
    <method>
      <name DesignerName="Initialize">_initialize</name>
      <comment>Initializes the object.
Pass android.webkit.JsResult from Java inline code to initialize instance.
Added in API level 1.
</comment>
      <returntype>String</returntype>
      <parameter>
        <name>ba</name>
        <type>anywheresoftware.b4a.BA</type>
      </parameter>
      <parameter>
        <name>AndroidWebkitJsResult</name>
        <type>Object</type>
      </parameter>
    </method>
    <method>
      <name DesignerName="toObject">_toobject</name>
      <comment>Returns Object as android.webkit.JsResult which can be used in Java Code.
Added in API level 1.
</comment>
      <returntype>Object</returntype>
    </method>
  </class>
  <version>1</version>
  <author>Ivica Golubovic</author>
</root>