<?xml version="1.0" encoding="UTF-8"?>
<root>
    <doclet-version-NOT-library-version>1.07</doclet-version-NOT-library-version>
    <class>
        <name>com.simplysoftware.Win32.Win32</name>
        <shortname>Win32</shortname>
        <owner>process</owner>
        <method>
            <name>RegWriteBinary</name>
            <comment>Writes a binary value to HKCU.</comment>
            <returntype>void</returntype>
            <parameter>
                <name>key</name>
                <type>java.lang.String</type>
            </parameter>
            <parameter>
                <name>valueName</name>
                <type>java.lang.String</type>
            </parameter>
            <parameter>
                <name>value</name>
                <type>byte[]</type>
            </parameter>
        </method>
        <method>
            <name>AllowSleep</name>
            <comment>Clears sleep prevention.</comment>
            <returntype>void</returntype>
        </method>
        <method>
            <name>RunWaitGetOutput</name>
            <comment>Runs a command, waits for it to finish, and returns its stdout output.</comment>
            <returntype>java.lang.String</returntype>
            <parameter>
                <name>command</name>
                <type>java.lang.String</type>
            </parameter>
        </method>
        <method>
            <name>SetWindowStyle</name>
            <comment>Sets the window style (GWL_STYLE).</comment>
            <returntype>void</returntype>
            <parameter>
                <name>hwndValue</name>
                <type>long</type>
            </parameter>
            <parameter>
                <name>style</name>
                <type>int</type>
            </parameter>
        </method>
        <method>
            <name>GetNetworkInterfaces</name>
            <comment>Returns a list of network interfaces as "Name:DisplayName".</comment>
            <returntype>java.lang.String[]</returntype>
        </method>
        <method>
            <name>CloseWindow</name>
            <comment>Closes a window (sends WM_CLOSE).</comment>
            <returntype>void</returntype>
            <parameter>
                <name>hwndValue</name>
                <type>long</type>
            </parameter>
        </method>
        <method>
            <name>SetClipboardText</name>
            <comment>Sets text to the clipboard.</comment>
            <returntype>boolean</returntype>
            <parameter>
                <name>text</name>
                <type>java.lang.String</type>
            </parameter>
        </method>
        <method>
            <name>GetActiveWindowHandle</name>
            <comment>Returns the handle (pointer value) of the active window.</comment>
            <returntype>long</returntype>
        </method>
        <method>
            <name>GetWorkAreaWidth</name>
            <comment>Returns the work area width (excluding taskbar).</comment>
            <returntype>int</returntype>
        </method>
        <method>
            <name>RunCommand</name>
            <comment>Runs a command using cmd.exe /c (like Windows Run dialog).</comment>
            <returntype>boolean</returntype>
            <parameter>
                <name>command</name>
                <type>java.lang.String</type>
            </parameter>
        </method>
        <method>
            <name>GetProcessMemoryMB</name>
            <comment>Returns memory usage (MB) of a process by PID, or -1 if unavailable.</comment>
            <returntype>int</returntype>
            <parameter>
                <name>pid</name>
                <type>int</type>
            </parameter>
        </method>
        <method>
            <name>GetMonitorCount</name>
            <comment>Returns the number of monitors.</comment>
            <returntype>int</returntype>
        </method>
        <method>
            <name>MouseRightClick</name>
            <comment>Sends a right mouse click.</comment>
            <returntype>void</returntype>
        </method>
        <method>
            <name>MoveWindow</name>
            <comment>Moves and resizes a window.</comment>
            <returntype>void</returntype>
            <parameter>
                <name>hwndValue</name>
                <type>long</type>
            </parameter>
            <parameter>
                <name>x</name>
                <type>int</type>
            </parameter>
            <parameter>
                <name>y</name>
                <type>int</type>
            </parameter>
            <parameter>
                <name>width</name>
                <type>int</type>
            </parameter>
            <parameter>
                <name>height</name>
                <type>int</type>
            </parameter>
            <parameter>
                <name>repaint</name>
                <type>boolean</type>
            </parameter>
        </method>
        <method>
            <name>GetDefaultGateway</name>
            <comment>Returns the default IPv4 gateway by parsing 'route print'.</comment>
            <returntype>java.lang.String</returntype>
        </method>
        <method>
            <name>MouseMove</name>
            <comment>Moves the mouse by dx, dy relative to current position.</comment>
            <returntype>void</returntype>
            <parameter>
                <name>dx</name>
                <type>int</type>
            </parameter>
            <parameter>
                <name>dy</name>
                <type>int</type>
            </parameter>
        </method>
        <method>
            <name>KeyDown</name>
            <comment>Sends a key down event.</comment>
            <returntype>void</returntype>
            <parameter>
                <name>vk</name>
                <type>int</type>
            </parameter>
        </method>
        <method>
            <name>ShellOpen</name>
            <comment>Opens a file or URL with the default associated application.</comment>
            <returntype>boolean</returntype>
            <parameter>
                <name>target</name>
                <type>java.lang.String</type>
            </parameter>
        </method>
        <method>
            <name>ServiceExists</name>
            <comment>Returns true if a service exists.</comment>
            <returntype>boolean</returntype>
            <parameter>
                <name>serviceName</name>
                <type>java.lang.String</type>
            </parameter>
        </method>
        <method>
            <name>GetWorkAreaHeight</name>
            <comment>Returns the work area height (excluding taskbar).</comment>
            <returntype>int</returntype>
        </method>
        <method>
            <name>RegWriteDword</name>
            <comment>Writes a DWORD value to HKCU.</comment>
            <returntype>void</returntype>
            <parameter>
                <name>key</name>
                <type>java.lang.String</type>
            </parameter>
            <parameter>
                <name>valueName</name>
                <type>java.lang.String</type>
            </parameter>
            <parameter>
                <name>value</name>
                <type>int</type>
            </parameter>
        </method>
        <method>
            <name>FileExists</name>
            <comment>Checks if a file exists.</comment>
            <returntype>boolean</returntype>
            <parameter>
                <name>path</name>
                <type>java.lang.String</type>
            </parameter>
        </method>
        <method>
            <name>RunWait</name>
            <comment>Runs a command and waits for it to finish.
    Returns exit code.</comment>
            <returntype>int</returntype>
            <parameter>
                <name>command</name>
                <type>java.lang.String</type>
            </parameter>
        </method>
        <method>
            <name>GetWindowStyle</name>
            <comment>Gets the window style (GWL_STYLE).</comment>
            <returntype>int</returntype>
            <parameter>
                <name>hwndValue</name>
                <type>long</type>
            </parameter>
        </method>
        <method>
            <name>RegDeleteKey</name>
            <comment>Deletes a key from HKCU.</comment>
            <returntype>void</returntype>
            <parameter>
                <name>key</name>
                <type>java.lang.String</type>
            </parameter>
        </method>
        <method>
            <name>GetSystemDirectory</name>
            <comment>Returns the system directory path.</comment>
            <returntype>java.lang.String</returntype>
        </method>
        <method>
            <name>GetMonitorRects</name>
            <comment>Returns monitor rectangles as [ [l,t,r,b], ... ].</comment>
            <returntype>int[]</returntype>
        </method>
        <method>
            <name>Hibernate</name>
            <comment>Hibernates the system.</comment>
            <returntype>void</returntype>
        </method>
        <method>
            <name>RegReadDword</name>
            <comment>Reads a DWORD value from HKCU.</comment>
            <returntype>int</returntype>
            <parameter>
                <name>key</name>
                <type>java.lang.String</type>
            </parameter>
            <parameter>
                <name>valueName</name>
                <type>java.lang.String</type>
            </parameter>
        </method>
        <method>
            <name>GetAppDataFolder</name>
            <comment>Returns the AppData folder path.</comment>
            <returntype>java.lang.String</returntype>
        </method>
        <method>
            <name>PreventSleep</name>
            <comment>Prevents system sleep until cleared.</comment>
            <returntype>void</returntype>
        </method>
        <method>
            <name>GetProcessorCount</name>
            <comment>Returns the number of processors.</comment>
            <returntype>int</returntype>
        </method>
        <method>
            <name>GetWindowRect</name>
            <comment>Returns the rectangle of a window.
    [left, top, right, bottom]</comment>
            <returntype>int[]</returntype>
            <parameter>
                <name>hwndValue</name>
                <type>long</type>
            </parameter>
        </method>
        <method>
            <name>SetWindowExStyle</name>
            <comment>Sets the extended window style (GWL_EXSTYLE).</comment>
            <returntype>void</returntype>
            <parameter>
                <name>hwndValue</name>
                <type>long</type>
            </parameter>
            <parameter>
                <name>style</name>
                <type>int</type>
            </parameter>
        </method>
        <method>
            <name>SendKey</name>
            <comment>Sends a single key press (virtual key code).</comment>
            <returntype>void</returntype>
            <parameter>
                <name>vk</name>
                <type>int</type>
            </parameter>
        </method>
        <method>
            <name>SetEnv</name>
            <comment>Sets an environment variable value for the current process.</comment>
            <returntype>boolean</returntype>
            <parameter>
                <name>name</name>
                <type>java.lang.String</type>
            </parameter>
            <parameter>
                <name>value</name>
                <type>java.lang.String</type>
            </parameter>
        </method>
        <method>
            <name>GetIPAddress</name>
            <comment>Returns the first non-loopback IPv4 address, or empty string if none found.</comment>
            <returntype>java.lang.String</returntype>
        </method>
        <method>
            <name>GetScreenWidth</name>
            <comment>Returns the primary screen width.</comment>
            <returntype>int</returntype>
        </method>
        <method>
            <name>ShowInExplorer</name>
            <comment>Shows a file in Explorer (selects it).</comment>
            <returntype>void</returntype>
            <parameter>
                <name>path</name>
                <type>java.lang.String</type>
            </parameter>
        </method>
        <method>
            <name>RestoreWindow</name>
            <comment>Restores a window.</comment>
            <returntype>void</returntype>
            <parameter>
                <name>hwndValue</name>
                <type>long</type>
            </parameter>
        </method>
        <method>
            <name>Shutdown</name>
            <comment>Shuts down Windows.</comment>
            <returntype>void</returntype>
        </method>
        <method>
            <name>GetIPAddresses</name>
            <comment>Returns all non-loopback IPv4 addresses.</comment>
            <returntype>java.lang.String[]</returntype>
        </method>
        <method>
            <name>GetWindowsDirectory</name>
            <comment>Returns the Windows directory path.</comment>
            <returntype>java.lang.String</returntype>
        </method>
        <method>
            <name>GetSystemCPUUsage</name>
            <comment>Returns accurate system-wide CPU usage percentage (0–100).</comment>
            <returntype>int</returntype>
        </method>
        <method>
            <name>GetEnv</name>
            <comment>Gets an environment variable value.</comment>
            <returntype>java.lang.String</returntype>
            <parameter>
                <name>name</name>
                <type>java.lang.String</type>
            </parameter>
        </method>
        <method>
            <name>MouseWheel</name>
            <comment>Scrolls the mouse wheel by the given delta (positive = up, negative = down).</comment>
            <returntype>void</returntype>
            <parameter>
                <name>delta</name>
                <type>int</type>
            </parameter>
        </method>
        <method>
            <name>GetProcessList</name>
            <comment>Returns a list of processes as "PID:Name".</comment>
            <returntype>java.lang.String[]</returntype>
        </method>
        <method>
            <name>GetClipboardText</name>
            <comment>Gets text from the clipboard.
    Returns empty string if unavailable.</comment>
            <returntype>java.lang.String</returntype>
        </method>
        <method>
            <name>RegReadBinary</name>
            <comment>Reads a binary value from HKCU.</comment>
            <returntype>byte[]</returntype>
            <parameter>
                <name>key</name>
                <type>java.lang.String</type>
            </parameter>
            <parameter>
                <name>valueName</name>
                <type>java.lang.String</type>
            </parameter>
        </method>
        <method>
            <name>GetMACAddress</name>
            <comment>Returns the MAC address of the first active IPv4 interface.</comment>
            <returntype>java.lang.String</returntype>
        </method>
        <method>
            <name>GetInterfaceAddresses</name>
            <comment>Returns IP addresses for a given interface name.</comment>
            <returntype>java.lang.String[]</returntype>
            <parameter>
                <name>interfaceName</name>
                <type>java.lang.String</type>
            </parameter>
        </method>
        <method>
            <name>EnumWindowsTitles</name>
            <comment>Enumerates top-level windows and returns their titles as an array.</comment>
            <returntype>java.lang.String[]</returntype>
        </method>
        <method>
            <name>GetActiveWindowTitle</name>
            <comment>Returns the title of the current foreground window.</comment>
            <returntype>java.lang.String</returntype>
        </method>
        <method>
            <name>RegReadString</name>
            <comment>Reads a string value from HKCU.</comment>
            <returntype>java.lang.String</returntype>
            <parameter>
                <name>key</name>
                <type>java.lang.String</type>
            </parameter>
            <parameter>
                <name>valueName</name>
                <type>java.lang.String</type>
            </parameter>
        </method>
        <method>
            <name>RegDeleteValue</name>
            <comment>Deletes a value from HKCU.</comment>
            <returntype>void</returntype>
            <parameter>
                <name>key</name>
                <type>java.lang.String</type>
            </parameter>
            <parameter>
                <name>valueName</name>
                <type>java.lang.String</type>
            </parameter>
        </method>
        <method>
            <name>RunWaitGetOutputFull</name>
            <comment>Runs a command, waits for it to finish, and returns both output and exit code.</comment>
            <returntype>java.lang.String</returntype>
            <parameter>
                <name>command</name>
                <type>java.lang.String</type>
            </parameter>
        </method>
        <method>
            <name>GetSystemBootTime</name>
            <comment>Returns system boot time as a formatted string.</comment>
            <returntype>java.lang.String</returntype>
        </method>
        <method>
            <name>GetWindowExStyle</name>
            <comment>Gets the extended window style (GWL_EXSTYLE).</comment>
            <returntype>int</returntype>
            <parameter>
                <name>hwndValue</name>
                <type>long</type>
            </parameter>
        </method>
        <method>
            <name>SetTopMost</name>
            <comment>Sets or clears the topmost flag for a window.</comment>
            <returntype>void</returntype>
            <parameter>
                <name>hwndValue</name>
                <type>long</type>
            </parameter>
            <parameter>
                <name>topMost</name>
                <type>boolean</type>
            </parameter>
        </method>
        <method>
            <name>GetDiskSpace</name>
            <comment>Returns disk space info for a path: "freeMB,totalMB,usableMB".</comment>
            <returntype>java.lang.String</returntype>
            <parameter>
                <name>path</name>
                <type>java.lang.String</type>
            </parameter>
        </method>
        <method>
            <name>Restart</name>
            <comment>Restarts Windows.</comment>
            <returntype>void</returntype>
        </method>
        <method>
            <name>SetFileAttributes</name>
            <comment>Sets file attributes (bitmask).</comment>
            <returntype>boolean</returntype>
            <parameter>
                <name>path</name>
                <type>java.lang.String</type>
            </parameter>
            <parameter>
                <name>attrs</name>
                <type>int</type>
            </parameter>
        </method>
        <method>
            <name>ServiceStop</name>
            <comment>Stops a service.</comment>
            <returntype>boolean</returntype>
            <parameter>
                <name>serviceName</name>
                <type>java.lang.String</type>
            </parameter>
        </method>
        <method>
            <name>GetScreenHeight</name>
            <comment>Returns the primary screen height.</comment>
            <returntype>int</returntype>
        </method>
        <method>
            <name>RunAsAdmin</name>
            <comment>Runs a command with UAC elevation (Run as Administrator).</comment>
            <returntype>boolean</returntype>
            <parameter>
                <name>command</name>
                <type>java.lang.String</type>
            </parameter>
        </method>
        <method>
            <name>MonitorOn</name>
            <comment>Turns the monitor on.</comment>
            <returntype>void</returntype>
        </method>
        <method>
            <name>MaximiseWindow</name>
            <comment>Maximises a window.</comment>
            <returntype>void</returntype>
            <parameter>
                <name>hwndValue</name>
                <type>long</type>
            </parameter>
        </method>
        <method>
            <name>BringToFront</name>
            <comment>Brings a window to the foreground using its handle.</comment>
            <returntype>boolean</returntype>
            <parameter>
                <name>hwndValue</name>
                <type>long</type>
            </parameter>
        </method>
        <method>
            <name>ServiceStart</name>
            <comment>Starts a service.</comment>
            <returntype>boolean</returntype>
            <parameter>
                <name>serviceName</name>
                <type>java.lang.String</type>
            </parameter>
        </method>
        <method>
            <name>MouseClick</name>
            <comment>Sends a left mouse click.</comment>
            <returntype>void</returntype>
        </method>
        <method>
            <name>RunGetOutput</name>
            <comment>Runs a command and returns its stdout output as a string.</comment>
            <returntype>java.lang.String</returntype>
            <parameter>
                <name>command</name>
                <type>java.lang.String</type>
            </parameter>
        </method>
        <method>
            <name>GetDesktopRect</name>
            <comment>Returns the desktop rectangle. [left, top, right, bottom]</comment>
            <returntype>int[]</returntype>
        </method>
        <method>
            <name>GetAvailablePhysicalMemoryMB</name>
            <comment>Returns available physical memory in MB.</comment>
            <returntype>long</returntype>
        </method>
        <method>
            <name>GetTaskbarRect</name>
            <comment>Returns the taskbar rectangle. [left, top, right, bottom] or zeros if not found.</comment>
            <returntype>int[]</returntype>
        </method>
        <method>
            <name>GetCurrentPID</name>
            <comment>Returns the current process ID.</comment>
            <returntype>int</returntype>
        </method>
        <method>
            <name>RunHidden</name>
            <comment>Runs a command hidden (no console window).</comment>
            <returntype>boolean</returntype>
            <parameter>
                <name>command</name>
                <type>java.lang.String</type>
            </parameter>
        </method>
        <method>
            <name>MonitorOff</name>
            <comment>Turns the monitor off.</comment>
            <returntype>void</returntype>
        </method>
        <method>
            <name>GetBatteryPercent</name>
            <comment>Returns battery percentage (0-100) or -1 if unknown.</comment>
            <returntype>int</returntype>
        </method>
        <method>
            <name>IsInterfaceUp</name>
            <comment>Returns whether the interface is up.</comment>
            <returntype>boolean</returntype>
            <parameter>
                <name>interfaceName</name>
                <type>java.lang.String</type>
            </parameter>
        </method>
        <method>
            <name>GetInterfaceIPv4</name>
            <comment>Returns the first IPv4 address for a specific interface name.</comment>
            <returntype>java.lang.String</returntype>
            <parameter>
                <name>interfaceName</name>
                <type>java.lang.String</type>
            </parameter>
        </method>
        <method>
            <name>RegKeyExists</name>
            <comment>Checks if a key exists in HKCU.</comment>
            <returntype>boolean</returntype>
            <parameter>
                <name>key</name>
                <type>java.lang.String</type>
            </parameter>
        </method>
        <method>
            <name>GetDocumentsFolder</name>
            <comment>Returns the Documents folder path.</comment>
            <returntype>java.lang.String</returntype>
        </method>
        <method>
            <name>KeyUp</name>
            <comment>Sends a key up event.</comment>
            <returntype>void</returntype>
            <parameter>
                <name>vk</name>
                <type>int</type>
            </parameter>
        </method>
        <method>
            <name>GetFileAttributes</name>
            <comment>Returns file attributes as a bitmask.</comment>
            <returntype>int</returntype>
            <parameter>
                <name>path</name>
                <type>java.lang.String</type>
            </parameter>
        </method>
        <method>
            <name>MinimiseWindow</name>
            <comment>Minimises a window.</comment>
            <returntype>void</returntype>
            <parameter>
                <name>hwndValue</name>
                <type>long</type>
            </parameter>
        </method>
        <method>
            <name>GetDesktopFolder</name>
            <comment>Returns the Desktop folder path.</comment>
            <returntype>java.lang.String</returntype>
        </method>
        <method>
            <name>RegWriteString</name>
            <comment>Writes a string value to HKCU.</comment>
            <returntype>void</returntype>
            <parameter>
                <name>key</name>
                <type>java.lang.String</type>
            </parameter>
            <parameter>
                <name>valueName</name>
                <type>java.lang.String</type>
            </parameter>
            <parameter>
                <name>value</name>
                <type>java.lang.String</type>
            </parameter>
        </method>
        <method>
            <name>ServiceGetStatus</name>
            <comment>Returns the status of a service as a string.</comment>
            <returntype>java.lang.String</returntype>
            <parameter>
                <name>serviceName</name>
                <type>java.lang.String</type>
            </parameter>
        </method>
        <method>
            <name>FlashWindow</name>
            <comment>Flashes a window in the taskbar.</comment>
            <returntype>void</returntype>
            <parameter>
                <name>hwndValue</name>
                <type>long</type>
            </parameter>
            <parameter>
                <name>count</name>
                <type>int</type>
            </parameter>
        </method>
        <method>
            <name>Sleep</name>
            <comment>Puts the system to sleep.</comment>
            <returntype>void</returntype>
        </method>
        <method>
            <name>GetParentPID</name>
            <comment>Returns the parent process ID.</comment>
            <returntype>int</returntype>
        </method>
        <method>
            <name>LockWorkstation</name>
            <comment>Locks the workstation (same as Win+L).</comment>
            <returntype>void</returntype>
        </method>
        <method>
            <name>GetActiveWindowClass</name>
            <comment>Returns the class name of the active window.</comment>
            <returntype>java.lang.String</returntype>
        </method>
        <method>
            <name>GetSystemUptime</name>
            <comment>Returns system uptime in milliseconds.</comment>
            <returntype>long</returntype>
        </method>
        <method>
            <name>GetWindowClass</name>
            <comment>Returns the class name of a window by handle.</comment>
            <returntype>java.lang.String</returntype>
            <parameter>
                <name>hwndValue</name>
                <type>long</type>
            </parameter>
        </method>
        <method>
            <name>GetTotalPhysicalMemoryMB</name>
            <comment>Returns total physical memory in MB.</comment>
            <returntype>long</returntype>
        </method>
        <field>
            <name>SC_MONITORPOWER</name>
            <comment></comment>
            <returntype>int</returntype>
        </field>
    </class>
    <version>1.0</version>
    <author>Peter Simpson</author>
    <dependsOn>jna-5.18.1.jar</dependsOn>
    <dependsOn>jna-platform-5.18.1.jar</dependsOn>
</root>
